{
  "name": "mlfoundations/open_clip",
  "description": "An open source implementation of CLIP.",
  "stars": 13774,
  "language": "Python",
  "topics": [
    "computer-vision",
    "contrastive-loss",
    "deep-learning",
    "language-model",
    "multi-modal-learning",
    "pretrained-models",
    "pytorch",
    "zero-shot-classification"
  ],
  "url": "https://github.com/mlfoundations/open_clip",
  "created": "2021-07-28T23:24:39Z",
  "tag": "GitHub",
  "pillar": "capabilities",
  "pillar_keywords": [
    "vision"
  ],
  "summary_cn": "OpenCLIP是CLIP模型的开源实现，支持多模态图文对比学习与零样本分类。对AI产品经理而言，它提供了免授权、可定制的多模态基座能力，可快速赋能图像检索、内容审核、推荐系统及AIGC文本引导等场景。其模块化架构与丰富预训练权重降低了研发门槛，助力企业低成本构建垂直领域多模态产品，加速商业化落地与生态创新。",
  "pm_relevance": 9
}